LICENSE.txt
MANIFEST.in
README.rst
setup.py
grcpass/__init__.py
grcpass/command_line.py
grcpass.egg-info/PKG-INFO
grcpass.egg-info/SOURCES.txt
grcpass.egg-info/dependency_links.txt
grcpass.egg-info/entry_points.txt
grcpass.egg-info/not-zip-safe
grcpass.egg-info/top_level.txt