Metadata-Version: 1.1
Name: grcpass
Version: 1.0.1
Summary: Simple script which scrapes off password from www.grc.com/passwords.htm
Home-page: https://github.com/arturtamborski/grcpass
Author: Artur Tamborski
Author-email: tamborskiartur@gmail.com
License: MIT
Download-URL: https://github.com/arturtamborski/grcpass/archive/1.0.1.tar.gz
Keywords: password generator
Platform: UNKNOWN
Classifier: Development Status :: 4 - Beta
Classifier: Environment :: Console
Classifier: Intended Audience :: System Administrators
Classifier: License :: OSI Approved :: MIT License
Classifier: Natural Language :: English
Classifier: Operating System :: OS Independent
Classifier: Programming Language :: Python
Classifier: Programming Language :: Python :: 2
Classifier: Programming Language :: Python :: 3
Classifier: Topic :: Security
